timedd/__init__.py
timedd/timedd.py
timedd-0.0.1.dist-info/LICENSE
timedd-0.0.1.dist-info/METADATA
timedd-0.0.1.dist-info/WHEEL
timedd-0.0.1.dist-info/top_level.txt
timedd-0.0.1.dist-info/RECORD
